metamorf/__init__.py
metamorf/constants.py
metamorf/help.py
metamorf/main.py
metamorf/configuration/configuration.yml
metamorf/configuration/properties.yml
metamorf/configuration/mysql/configuration_data_mysql.yml
metamorf/configuration/mysql/configuration_metadata_mysql.yml
metamorf/configuration/postgresql/configuration_data_postgresql.yml
metamorf/configuration/postgresql/configuration_metadata_postgresql.yml
metamorf/configuration/snowflake/configuration_data_snowflake.yml
metamorf/configuration/snowflake/configuration_metadata_snowflake.yml
metamorf/configuration/sqlite/configuration_data_sqlite.yml
metamorf/configuration/sqlite/configuration_metadata_sqlite.yml
metamorf/engines/__init__.py
metamorf/engines/engine.py
metamorf/engines/engine_api.py
metamorf/engines/engine_backup.py
metamorf/engines/engine_commit.py
metamorf/engines/engine_delete.py
metamorf/engines/engine_deploy.py
metamorf/engines/engine_deploy_example.py
metamorf/engines/engine_download.py
metamorf/engines/engine_files.py
metamorf/engines/engine_init.py
metamorf/engines/engine_manifest.py
metamorf/engines/engine_metadata.py
metamorf/engines/engine_output.py
metamorf/engines/engine_process.py
metamorf/engines/engine_recover.py
metamorf/engines/engine_restore.py
metamorf/engines/engine_run.py
metamorf/engines/engine_upload.py
metamorf/engines/engine_validate.py
metamorf/entry/ENTRY_AGGREGATORS.csv
metamorf/entry/ENTRY_DATASET_MAPPINGS.csv
metamorf/entry/ENTRY_DATASET_RELATIONSHIPS.csv
metamorf/entry/ENTRY_DV_ENTITY.csv
metamorf/entry/ENTRY_DV_MAPPINGS.csv
metamorf/entry/ENTRY_DV_PROPERTIES.csv
metamorf/entry/ENTRY_ENTITY.csv
metamorf/entry/ENTRY_FILES.csv
metamorf/entry/ENTRY_FILTERS.csv
metamorf/entry/ENTRY_HAVING.csv
metamorf/entry/ENTRY_ORDER.csv
metamorf/entry/ENTRY_PATH.csv
metamorf/initialization/mysql/init_example_data_mysql.sql
metamorf/initialization/mysql/init_example_metadata_mysql.sql
metamorf/initialization/mysql/init_mysql.sql
metamorf/initialization/mysql/pre_init_mysql.sql
Metamorf-0.5.1.dist-info/LICENSE.md
Metamorf-0.5.1.dist-info/METADATA
Metamorf-0.5.1.dist-info/WHEEL
Metamorf-0.5.1.dist-info/entry_points.txt
Metamorf-0.5.1.dist-info/top_level.txt
Metamorf-0.5.1.dist-info/RECORD
