Metadata-Version: 2.1
Name: Metamorf
Version: 0.5.1
Summary: Metadata Suite to build and manage your Datawarehouse
Author-email: Guillermo Aumatell <guillermoaumatell@gmail.com>
Project-URL: Homepage, https://github.com/gausalom/metamorf
Project-URL: Bug Tracker, https://github.com/gausalom/metamorf/issues
Classifier: Programming Language :: Python :: 3
Classifier: License :: OSI Approved :: Apache Software License
Classifier: Operating System :: Microsoft :: Windows
Classifier: Operating System :: POSIX :: Linux
Requires-Python: >=3.10
License-File: LICENSE.md
Requires-Dist: snowflake-connector-python
Requires-Dist: PyYAML
Requires-Dist: Flask
Requires-Dist: psycopg2-binary
Requires-Dist: mysql-connector-python
